odoo_install/instalaservicio.py
odoo_install/configuranginx.py
odoo_install/instaladorapt.py
odoo_install/postgres.py
odoo_install/stopcalling.py
odoo_install/replace.py
odoo_install/loggeador.py
odoo_install/odoo_install.py
odoo_install/dependencias.py
odoo_install/_init_.py
odoo_install/instalagit.py
odoo_install-0.1.dist-info/DESCRIPTION.rst
odoo_install-0.1.dist-info/dependency_links.txt
odoo_install-0.1.dist-info/METADATA
odoo_install-0.1.dist-info/WHEEL
odoo_install-0.1.dist-info/top_level.txt
odoo_install-0.1.dist-info/pbr.json
odoo_install-0.1.dist-info/metadata.json
odoo_install-0.1.dist-info/RECORD
