Metadata-Version: 2.0
Name: odoo-install
Version: 0.1
Summary: Odoo installer.
Home-page: http://github.com/rubencabrera/odooinstall
Author: Rubén Cabrera
Author-email: rcabrera@bisnesmart.com
License: AGPL
Platform: UNKNOWN
Requires-Dist: subprocess32
Requires-Dist: apt
Requires-Dist: dateutil
Requires-Dist: decorator
Requires-Dist: docutils
Requires-Dist: feedparser
Requires-Dist: gdata
Requires-Dist: gevent
Requires-Dist: imaging
Requires-Dist: jinja2
Requires-Dist: ldap
Requires-Dist: libxslt1
Requires-Dist: lxml
Requires-Dist: mako
Requires-Dist: mock
Requires-Dist: openid
Requires-Dist: passlib
Requires-Dist: psutil
Requires-Dist: psycopg2
Requires-Dist: pybabel
Requires-Dist: pydot
Requires-Dist: pyparsing
Requires-Dist: pypdf
Requires-Dist: reportlab
Requires-Dist: requests
Requires-Dist: simplejson
Requires-Dist: pytz
Requires-Dist: unittest2
Requires-Dist: vatnumber
Requires-Dist: vobject
Requires-Dist: werkzeug
Requires-Dist: xlwt
Requires-Dist: pyyaml
Requires-Dist: unicodecsv
